wzmsgpackrpc
