Metadata-Version: 1.0
Name: wzmsgpackrpc
Version: 0.2.1
Summary: MessagePack-RPC implementation using Whizzer
Home-page: http://bitbucket.org/bfrog/wzmsgpackrpc
Author: Tom Burdick
Author-email: thomas.burdick@gmail.com
License: MIT
Platform: UNKNOWN
Classifier: Intended Audience :: Developers
Classifier: License :: OSI Approved :: MIT License
Classifier: Programming Language :: Python
Classifier: Programming Language :: Python :: 2
Classifier: Topic :: Software Development :: Libraries :: Python Modules
Classifier: Topic :: System :: Networking
Classifier: Topic :: Internet
